odoo/addons/bank_statement_check_number/README.rst
odoo/addons/bank_statement_check_number/__init__.py
odoo/addons/bank_statement_check_number/__manifest__.py
odoo/addons/bank_statement_check_number/i18n/bank_statement_check_number.pot
odoo/addons/bank_statement_check_number/i18n/it.po
odoo/addons/bank_statement_check_number/models/__init__.py
odoo/addons/bank_statement_check_number/models/account_bank_statement.py
odoo/addons/bank_statement_check_number/readme/CONTRIBUTORS.rst
odoo/addons/bank_statement_check_number/readme/DESCRIPTION.rst
odoo/addons/bank_statement_check_number/static/description/icon.png
odoo/addons/bank_statement_check_number/static/description/index.html
odoo/addons/bank_statement_check_number/tests/__init__.py
odoo/addons/bank_statement_check_number/tests/test_check_number.py
odoo/addons/bank_statement_check_number/views/account_bank_statement_views.xml
odoo_addon_bank_statement_check_number-16.0.1.0.0.4.dist-info/METADATA
odoo_addon_bank_statement_check_number-16.0.1.0.0.4.dist-info/WHEEL
odoo_addon_bank_statement_check_number-16.0.1.0.0.4.dist-info/top_level.txt
odoo_addon_bank_statement_check_number-16.0.1.0.0.4.dist-info/RECORD
