Metadata-Version: 2.1
Name: odoo-addon-bank_statement_check_number
Version: 16.0.1.0.0.4
Summary: Add the check number in the bank statements
Home-page: https://github.com/OCA/account-reconcile
Author: Ecosoft, Odoo Community Association (OCA)
Author-email: support@odoo-community.org
License: AGPL-3
Classifier: Programming Language :: Python
Classifier: Framework :: Odoo
Classifier: Framework :: Odoo :: 16.0
Classifier: License :: OSI Approved :: GNU Affero General Public License v3
Classifier: Development Status :: 3 - Alpha
Requires-Python: >=3.10
Requires-Dist: odoo-addon-account-move-line-check-number<16.1dev,>=16.0dev
Requires-Dist: odoo-addon-account-statement-base<16.1dev,>=16.0dev
Requires-Dist: odoo<16.1dev,>=16.0a
